patroni_cli/__init__.py
patroni_cli/patroni_cli.py
patroni_cli-0.1.2.dist-info/LICENSE
patroni_cli-0.1.2.dist-info/METADATA
patroni_cli-0.1.2.dist-info/WHEEL
patroni_cli-0.1.2.dist-info/entry_points.txt
patroni_cli-0.1.2.dist-info/top_level.txt
patroni_cli-0.1.2.dist-info/RECORD
