Metadata-Version: 2.1
Name: patroni-cli
Version: 0.1.2
Summary: A CLI tool to manage Patroni cluster, elect new leaders, and perform switchover.
Author-email: Brian Hartford <bh419@protonmail.com>
License: MIT
Keywords: patroni,cluster,failover,switchover
Classifier: Programming Language :: Python :: 3
Classifier: License :: OSI Approved :: MIT License
Classifier: Operating System :: OS Independent
Requires-Python: >=3.7
License-File: LICENSE
Requires-Dist: requests>=2.28.1
